code_debugger93/__init__.py
code_debugger93-0.0.0.dist-info/METADATA
code_debugger93-0.0.0.dist-info/WHEEL
code_debugger93-0.0.0.dist-info/top_level.txt
code_debugger93-0.0.0.dist-info/RECORD
